to_uv/__init__.py
to_uv/main.py
to_uv-0.1.0.dist-info/METADATA
to_uv-0.1.0.dist-info/WHEEL
to_uv-0.1.0.dist-info/entry_points.txt
to_uv-0.1.0.dist-info/RECORD
