Metadata-Version: 2.3
Name: to-uv
Version: 0.1.0
Summary: Migrate to 'uv' from other python package and project managers.
Project-URL: Pull Requests, https://github.com/seapagan/to-uv/pulls
Project-URL: Bug Tracker, https://github.com/seapagan/to-uv/issues
Project-URL: Changelog, https://github.com/seapagan/to-uv/blob/main/CHANGELOG.md
Project-URL: Repository, https://github.com/seapagan/to-uv
Author-email: Grant Ramsay <seapagan@gmail.com>
Requires-Python: >=3.9
Requires-Dist: pydantic>=2.9.2
Requires-Dist: rich>=13.9.3
Requires-Dist: typer>=0.12.5
